prettylist.py
setup.py
prettylist.egg-info/PKG-INFO
prettylist.egg-info/SOURCES.txt
prettylist.egg-info/dependency_links.txt
prettylist.egg-info/top_level.txt