Metadata-Version: 1.0
Name: prettylist
Version: 0.1.9
Summary: A simple Python library for easily displaying tabular data in a visually appealing ASCII table format
Home-page: http://github.com/libraries/prettylist
Author: lacewing.cc
Author-email: lacewing.cc@outlook.com
License: BSD (3 clause)
Platform: UNKNOWN
